hestia_logger/__init__.py
hestia_logger/internal_logger.py
hestia_logger/main.py
hestia_logger/core/__init__.py
hestia_logger/core/async_logger.py
hestia_logger/core/config.py
hestia_logger/core/custom_logger.py
hestia_logger/core/formatters.py
hestia_logger/decorators/__init__.py
hestia_logger/decorators/decorators.py
hestia_logger/handlers/__init__.py
hestia_logger/handlers/console_handler.py
hestia_logger/handlers/elasticsearch_handler.py
hestia_logger/handlers/file_handler.py
hestia_logger/middlewares/__init__.py
hestia_logger/middlewares/middleware.py
hestia_logger/utils/__init__.py
hestia_logger/utils/requests_logger.py
hestia_logger-1.3.1.dist-info/METADATA
hestia_logger-1.3.1.dist-info/WHEEL
hestia_logger-1.3.1.dist-info/licenses/LICENSE
hestia_logger-1.3.1.dist-info/RECORD
