Metadata-Version: 2.4
Name: hestia-logger
Version: 1.3.1
Summary: HESTIA is a high-performance, structured logging system for Python applications. Supports async logging, Elastic Stack integration, structured JSON logs, and colorized console output.
Project-URL: Homepage, https://github.com/fox-techniques/hestia-logger
Project-URL: Documentation, https://fox-techniques.github.io/hestia-logger
Project-URL: Repository, https://github.com/fox-techniques/hestia-logger
Author-email: FOX Techniques <ali.nabbi@fox-techniques.com>
License: Apache-2.0
License-File: LICENSE
Keywords: async,elasticsearch,fastapi,logging,microservices
Classifier: Development Status :: 5 - Production/Stable
Classifier: Intended Audience :: Developers
Classifier: License :: OSI Approved :: Apache Software License
Classifier: Programming Language :: Python :: 3
Classifier: Programming Language :: Python :: 3.11
Classifier: Programming Language :: Python :: 3.12
Classifier: Programming Language :: Python :: 3.13
Classifier: Topic :: System :: Logging
Requires-Python: >=3.11
Requires-Dist: aiofiles<25.0.0,>=24.1.0
Requires-Dist: coloredlogs<16.0.0,>=15.0.1
Requires-Dist: colorlog<7.0.0,>=6.9.0
Requires-Dist: elasticsearch<9.0.0,>=8.17.2
Requires-Dist: fastapi<0.116.0,>=0.115.11
Requires-Dist: httpx<0.29.0,>=0.28.1
Requires-Dist: python-dotenv<2.0.0,>=1.0.1
Requires-Dist: python-json-logger<4.0.0,>=3.2.1
Requires-Dist: requests<3.0.0,>=2.32.3
Requires-Dist: sqlalchemy<3.0.0,>=2.0.41
Requires-Dist: structlog<26.0.0,>=25.1.0
